.gitignore
README.txt
bootstrap.py
setup.py
test-plone-4.2.x.cfg
docs/HISTORY.txt
plone/__init__.py
plone.app.stagingbehavior.egg-info/PKG-INFO
plone.app.stagingbehavior.egg-info/SOURCES.txt
plone.app.stagingbehavior.egg-info/dependency_links.txt
plone.app.stagingbehavior.egg-info/entry_points.txt
plone.app.stagingbehavior.egg-info/namespace_packages.txt
plone.app.stagingbehavior.egg-info/not-zip-safe
plone.app.stagingbehavior.egg-info/requires.txt
plone.app.stagingbehavior.egg-info/top_level.txt
plone/app/__init__.py
plone/app/stagingbehavior/__init__.py
plone/app/stagingbehavior/configure.zcml
plone/app/stagingbehavior/copier.py
plone/app/stagingbehavior/interfaces.py
plone/app/stagingbehavior/policy.py
plone/app/stagingbehavior/relation.py
plone/app/stagingbehavior/stagingbehavior.txt
plone/app/stagingbehavior/utils.py
plone/app/stagingbehavior/browser/__init__.py
plone/app/stagingbehavior/browser/configure.zcml
plone/app/stagingbehavior/browser/control.py
plone/app/stagingbehavior/browser/info.py
plone/app/stagingbehavior/browser/info_baseline.pt
plone/app/stagingbehavior/profiles/testfixture/metadata.xml
plone/app/stagingbehavior/profiles/testfixture/portal_placeful_workflow.xml
plone/app/stagingbehavior/profiles/testfixture/repositorytool.xml
plone/app/stagingbehavior/profiles/testfixture/types.xml
plone/app/stagingbehavior/profiles/testfixture/workflows.xml
plone/app/stagingbehavior/profiles/testfixture/portal_placeful_workflow/working-copy.xml
plone/app/stagingbehavior/profiles/testfixture/types/stageable_type.xml
plone/app/stagingbehavior/profiles/testfixture/types/test_folder.xml
plone/app/stagingbehavior/profiles/testfixture/workflows/workingcopy_workflow/definition.xml
plone/app/stagingbehavior/tests/__init__.py
plone/app/stagingbehavior/tests/base.py
plone/app/stagingbehavior/tests/folder.xml
plone/app/stagingbehavior/tests/regressiontests.txt
plone/app/stagingbehavior/tests/stageable_type.xml
plone/app/stagingbehavior/tests/test_annotations.py
plone/app/stagingbehavior/tests/test_doctest.py
plone/app/stagingbehavior/tests/test_interfaces.py