Metadata-Version: 1.1
Name: plone.app.stagingbehavior
Version: 0.1
Summary: Provides a behavior for using plone.app.iterate with dexterity content types
Home-page: http://plone.org/products/dexterity
Author: Jonas Baumann
Author-email: dexterity-development@googlegroups.com
License: GPL
Keywords: plone dexterity behavior iterate staging
Platform: UNKNOWN
Classifier: Programming Language :: Python
Classifier: Topic :: Software Development :: Libraries :: Python Modules
